pydantic_diagram/__init__.py
pydantic_diagram/cli.py
pydantic_diagram/core.py
pydantic_diagram/py.typed
pydantic_diagram-0.1.5.dist-info/METADATA
pydantic_diagram-0.1.5.dist-info/WHEEL
pydantic_diagram-0.1.5.dist-info/entry_points.txt
pydantic_diagram-0.1.5.dist-info/licenses/LICENSE
pydantic_diagram-0.1.5.dist-info/RECORD
