Metadata-Version: 2.4
Name: pydantic-diagram
Version: 0.1.5
Summary: Generate ERD-style D2 diagrams from Pydantic models
Project-URL: Homepage, https://github.com/yourusername/pydantic-diagram
Project-URL: Repository, https://github.com/yourusername/pydantic-diagram
Author-email: Your Name <you@example.com>
License-Expression: MIT
License-File: LICENSE
Keywords: d2,diagram,erd,pydantic,visualization
Classifier: Development Status :: 3 - Alpha
Classifier: Intended Audience :: Developers
Classifier: License :: OSI Approved :: MIT License
Classifier: Programming Language :: Python :: 3
Classifier: Programming Language :: Python :: 3.10
Classifier: Programming Language :: Python :: 3.11
Classifier: Programming Language :: Python :: 3.12
Classifier: Topic :: Software Development :: Documentation
Classifier: Typing :: Typed
Requires-Python: >=3.10
Requires-Dist: pydantic>=2.0
Requires-Dist: typenames>=2.1.0
Provides-Extra: dev
Requires-Dist: pytest>=7.0; extra == 'dev'
Requires-Dist: ruff>=0.1.0; extra == 'dev'
